ComplexPy/ComplexPy.py
ComplexPy/__init__.py
ComplexPy-0.0.1.dist-info/METADATA
ComplexPy-0.0.1.dist-info/WHEEL
ComplexPy-0.0.1.dist-info/top_level.txt
ComplexPy-0.0.1.dist-info/RECORD
