Metadata-Version: 2.1
Name: ComplexPy
Version: 0.0.1
Summary: A Python library for handling calculations of complex number.
Author: waffelz
Author-email: **Don't contact me via email** -- use discord instead, my user is @waffelz0212
Requires-Python: >=3.6
